MANIFEST.in
README.txt
all_tests.py
ez_setup.py
setup.cfg
setup.py
docs/api-objects.txt
docs/class-tree.html
docs/crarr.png
docs/epydoc.css
docs/epydoc.js
docs/exceptions.AssertionError-class.html
docs/frames.html
docs/gchecky-module.html
docs/gchecky-pysrc.html
docs/gchecky.controller-module.html
docs/gchecky.controller-pysrc.html
docs/gchecky.controller.ControllerContext-class.html
docs/gchecky.controller.ControllerLevel_1-class.html
docs/gchecky.controller.ControllerLevel_2-class.html
docs/gchecky.controller.DataError-class.html
docs/gchecky.controller.GcheckyError-class.html
docs/gchecky.controller.HandlerError-class.html
docs/gchecky.controller.LibraryError-class.html
docs/gchecky.controller.ProcessingException-class.html
docs/gchecky.controller.SystemError-class.html
docs/gchecky.controller.html_order-class.html
docs/gchecky.data-module.html
docs/gchecky.data-pysrc.html
docs/gchecky.data.CountryCode-class.html
docs/gchecky.data.PresentOrNot-class.html
docs/gchecky.gxml-module.html
docs/gchecky.gxml-pysrc.html
docs/gchecky.gxml.Any-class.html
docs/gchecky.gxml.Boolean-class.html
docs/gchecky.gxml.Complex-class.html
docs/gchecky.gxml.Decimal-class.html
docs/gchecky.gxml.Document-class.html
docs/gchecky.gxml.DocumentManager-class.html
docs/gchecky.gxml.Double-class.html
docs/gchecky.gxml.Email-class.html
docs/gchecky.gxml.Field-class.html
docs/gchecky.gxml.Html-class.html
docs/gchecky.gxml.ID-class.html
docs/gchecky.gxml.IP-class.html
docs/gchecky.gxml.Integer-class.html
docs/gchecky.gxml.LanguageCode-class.html
docs/gchecky.gxml.List-class.html
docs/gchecky.gxml.Long-class.html
docs/gchecky.gxml.Node-class.html
docs/gchecky.gxml.NodeManager-class.html
docs/gchecky.gxml.Pattern-class.html
docs/gchecky.gxml.Phone-class.html
docs/gchecky.gxml.String-class.html
docs/gchecky.gxml.Timestamp-class.html
docs/gchecky.gxml.Url-class.html
docs/gchecky.gxml.Zip-class.html
docs/gchecky.model-module.html
docs/gchecky.model-pysrc.html
gchecky.egg-info/PKG-INFO
gchecky.egg-info/SOURCES.txt
gchecky.egg-info/dependency_links.txt
gchecky.egg-info/requires.txt
gchecky.egg-info/top_level.txt
