Metadata-Version: 1.0
Name: gchecky
Version: 0.2.1
Summary: Python wrapper for Google Checkout API Level 2
Home-page: http://gchecky.googlecode.com
Author: Evgeniy Tarassov
Author-email: etarassov@gmail.com
License: Apache License 2.0
Platform: UNKNOWN
